{
  "factions": [
    {
      "id": "faction_01_deep",
      "name": "Deep Bureaucracy",
      "description": "Influence bloc obsessed with absurd political decisions.",
      "color": "#1a1a2e",
      "tags": [
        "order",
        "paperwork"
      ]
    },
    {
      "id": "faction_02_meme",
      "name": "Meme Syndicate",
      "description": "Influence bloc obsessed with absurd political decisions.",
      "color": "#16213e",
      "tags": [
        "memes",
        "viral"
      ]
    },
    {
      "id": "faction_03_shadow",
      "name": "Shadow Lobbies",
      "description": "Influence bloc obsessed with absurd political decisions.",
      "color": "#0f3460",
      "tags": [
        "economy",
        "influence"
      ]
    },
    {
      "id": "faction_04_crisis",
      "name": "Crisis Cabal",
      "description": "Influence bloc obsessed with absurd political decisions.",
      "color": "#e94560",
      "tags": [
        "crisis",
        "panic"
      ]
    },
    {
      "id": "faction_05_spin",
      "name": "Spin Doctors",
      "description": "Influence bloc obsessed with absurd political decisions.",
      "color": "#f1f1f1",
      "tags": [
        "media",
        "spin"
      ]
    },
    {
      "id": "faction_06_international",
      "name": "International League",
      "description": "Influence bloc obsessed with absurd political decisions.",
      "color": "#1a1a2e",
      "tags": [
        "diplomacy",
        "reputation"
      ]
    },
    {
      "id": "faction_07_grassroots",
      "name": "Grassroots Choir",
      "description": "Influence bloc obsessed with absurd political decisions.",
      "color": "#16213e",
      "tags": [
        "approval",
        "populism"
      ]
    },
    {
      "id": "faction_08_absurdity",
      "name": "Absurdity Cult",
      "description": "Influence bloc obsessed with absurd political decisions.",
      "color": "#0f3460",
      "tags": [
        "absurd",
        "spectacle"
      ]
    }
  ]
}